pydaconf_plugins_vault/__init__.py
pydaconf_plugins_vault/config_model.py
pydaconf_plugins_vault/utils.py
pydaconf_plugins_vault/vault.py
pydaconf_plugins_vault-0.1.0.dist-info/entry_points.txt
pydaconf_plugins_vault-0.1.0.dist-info/licenses/LICENSE
pydaconf_plugins_vault-0.1.0.dist-info/WHEEL
pydaconf_plugins_vault-0.1.0.dist-info/METADATA
pydaconf_plugins_vault-0.1.0.dist-info/RECORD
