Metadata-Version: 2.4
Name: pydaconf-plugins-vault
Version: 0.1.0
Summary: Pydaconf Plugic for Hashicorp Vault and OpenBao
Author-email: Borislav Varadinov <borislav.varadinov@outlook.com>
Requires-Python: >=3.10
Classifier: Development Status :: 4 - Beta
Classifier: Intended Audience :: Developers
Classifier: License :: OSI Approved :: MIT License
Classifier: Programming Language :: Python :: 3
Classifier: Programming Language :: Python :: 3 :: Only
Classifier: Programming Language :: Python :: 3.10
Classifier: Programming Language :: Python :: 3.11
Classifier: Programming Language :: Python :: 3.12
Classifier: Programming Language :: Python :: 3.13
Classifier: Topic :: Internet
Classifier: Topic :: Software Development :: Libraries :: Python Modules
Classifier: Topic :: Software Development :: Libraries
Classifier: Topic :: Software Development
Classifier: Typing :: Typed
License-File: LICENSE
Requires-Dist: hvac>=2.3.0
Requires-Dist: pydaconf>=0.3.0
Project-URL: Documentation, https://github.com/varadinov/pydaconf-plugins-vault
Project-URL: Homepage, https://github.com/varadinov/pydaconf-plugins-vault
Project-URL: Issues, https://github.com/varadinov/pydaconf-plugins-vault/issues
Project-URL: Repository, https://github.com/varadinov/pydaconf-plugins-vault
